testchameleon/__init__.py
testchameleon/_version.py
testchameleon/algorithm.py
testchameleon-1.0.dist-info/LICENSE
testchameleon-1.0.dist-info/METADATA
testchameleon-1.0.dist-info/WHEEL
testchameleon-1.0.dist-info/top_level.txt
testchameleon-1.0.dist-info/RECORD
