Metadata-Version: 2.1
Name: testchameleon
Version: 1.0
Summary: this is a module made by kevin
Home-page: UNKNOWN
Author: jiaxing
Author-email: UNKNOWN
License: UNKNOWN
Platform: UNKNOWN
